oobleck/__init__.py
oobleck/cli.py
oobleck/elastic/__init__.py
oobleck/elastic/agent.py
oobleck/elastic/master_service_pb2.py
oobleck/elastic/master_service_pb2.pyi
oobleck/elastic/master_service_pb2_grpc.py
oobleck/elastic/run.py
oobleck/engine/__init__.py
oobleck/engine/configuration_engine.py
oobleck/engine/execution_engine.py
oobleck/engine/pipeline_instantiator.py
oobleck/engine/plugin.py
oobleck/planning/__init__.py
oobleck/planning/planner.cpython-310-x86_64-linux-gnu.so
oobleck/planning/planner.pyi
oobleck/planning/profiler.py
oobleck-0.1.1.dist-info/LICENSE
oobleck-0.1.1.dist-info/METADATA
oobleck-0.1.1.dist-info/WHEEL
oobleck-0.1.1.dist-info/entry_points.txt
oobleck-0.1.1.dist-info/top_level.txt
oobleck-0.1.1.dist-info/RECORD
