Metadata-Version: 2.1
Name: oobleck
Version: 0.1.1
Summary: A framework for efficient fault tolerance in large scale distributed training with pipeline template.
Author-email: Insu Jang <insujang@umich.edu>
Maintainer-email: Insu Jang <insujang@umich.edu>
License: Copyright (c) 2023 SymbioticLab, The University of Michigan
Requires-Python: >=3.10
License-File: LICENSE
Requires-Dist: torch
Requires-Dist: transformers >=4.36.0
Requires-Dist: colossalai ==0.3.6
Requires-Dist: click
Requires-Dist: loguru
Requires-Dist: fabric
Requires-Dist: cornstarch
Requires-Dist: grpcio
Requires-Dist: pulp
Provides-Extra: dev
Requires-Dist: torch >=2.1.0 ; extra == 'dev'
Requires-Dist: ruff ; extra == 'dev'
Requires-Dist: black >=23.0 ; extra == 'dev'
Requires-Dist: isort >=5.12 ; extra == 'dev'
Requires-Dist: pytest ; extra == 'dev'
Requires-Dist: pytest-mock ; extra == 'dev'
Requires-Dist: pytest-grpc ; extra == 'dev'
Requires-Dist: grpcio-tools ; extra == 'dev'
Requires-Dist: datasets ; extra == 'dev'
